blender_plots/__init__.py
blender_plots/arrows.py
blender_plots/blender_utils.py
blender_plots/marker_utils.py
blender_plots/plots_base.py
blender_plots/scatter.py
blender_plots/scene_utils.py
blender_plots/surface.py
blender_plots-1.0.13.dist-info/LICENSE
blender_plots-1.0.13.dist-info/METADATA
blender_plots-1.0.13.dist-info/WHEEL
blender_plots-1.0.13.dist-info/top_level.txt
blender_plots-1.0.13.dist-info/RECORD
