Metadata-Version: 2.1
Name: blender-plots
Version: 1.0.13
Summary: Plotting API for Blender
Home-page: https://github.com/Linusnie/blender-plots
Author: Linus Härenstam-Nielsen
Requires-Python: >=3.10
License-File: LICENSE
